MANIFEST.in
README.md
setup.py
gum/__init__.py
gum/app.py
gum/constants.py
gum/run.py
gum/controllers/__init__.py
gum/controllers/editor.py
gum/controllers/effect.py
gum/controllers/player.py
gum/data/gum-128.png
gum/data/test/test1.wav
gum/data/test/test2.wav
gum/data/test/test3.wav
gum/fast/fast.c
gum/fast/fast.h
gum/fx/__init__.py
gum/fx/_svf.c
gum/fx/bitcrusher.py
gum/fx/convolution.py
gum/fx/monoize.py
gum/fx/svf.py
gum/fx/volume.py
gum/lib/__init__.py
gum/lib/edit.py
gum/lib/event.py
gum/lib/history.py
gum/lib/mock.py
gum/models/__init__.py
gum/models/clipboard.py
gum/models/cursor.py
gum/models/graph.py
gum/models/selection.py
gum/models/sound.py
gum/scripts/gum
gum/views/__init__.py
gum/views/effect.py
gum/views/filedialog.py
gum/views/ui.py
gum/views/waveform.py
gum_audio.egg-info/PKG-INFO
gum_audio.egg-info/SOURCES.txt
gum_audio.egg-info/dependency_links.txt
gum_audio.egg-info/requires.txt
gum_audio.egg-info/top_level.txt