Metadata-Version: 1.1
Name: gum-audio
Version: 0.8.3.2
Summary: Gum Audio Editor
Home-page: https://github.com/stackp/Gum
Author: Pierre
Author-email: stackp@online.fr
License: BSD License
Platform: UNKNOWN
Classifier: Development Status :: 4 - Beta
Classifier: Environment :: X11 Applications :: GTK
Classifier: Intended Audience :: End Users/Desktop
Classifier: License :: OSI Approved :: BSD License
Classifier: Natural Language :: English
Classifier: Operating System :: POSIX :: Linux
Classifier: Programming Language :: Python
Classifier: Topic :: Multimedia :: Sound/Audio :: Editors
Requires: PyGTK
Requires: numpy
Requires: pyalsaaudio (>=0.6)
Requires: samplerate
Requires: pysndfile
Requires: enum34
